seasonal_behavior_deviation/__init__.py
seasonal_behavior_deviation/anomaly_detection.py
seasonal_behavior_deviation/preprocess.py
seasonal_behavior_deviation/result.py
seasonal_behavior_deviation/util.py
seasonal_behavior_deviation-0.1.4.dist-info/AUTHORS.rst
seasonal_behavior_deviation-0.1.4.dist-info/LICENSE.txt
seasonal_behavior_deviation-0.1.4.dist-info/METADATA
seasonal_behavior_deviation-0.1.4.dist-info/WHEEL
seasonal_behavior_deviation-0.1.4.dist-info/top_level.txt
seasonal_behavior_deviation-0.1.4.dist-info/RECORD
